Language/verilog/third/timer/Tr.v
module Tr (/*AUTOARG*/
   // Outputs
   led, q,
   // Inputs
   res, clk, e
   ) ;
   input  res, clk, e;
   output led;
   output [4:0] q;

   reg          led, q;

   always @ (negedge res, posedge clk) begin
      if (!res) begin
         q <= 0;
         led <= 0;
      end
      else if (e) begin
         q <= q + 1;
         if (q == 5'b10100)
           led = ~led;
      end
   end

endmodule // Tr

Language/verilog/third/timer/tTr.v
`timescale 1ns/1ns

module tTr (/*AUTOARG*/) ;
   reg clk, e, resetn;
   wire [4:0] q;
   wire       led;

   initial begin
      e = 1;
      clk = 1;
      resetn = 1;
      #10000 $stop;
   end

   always #25 clk = ~clk;
   always #750 resetn = ~resetn;


   Tr test(led, q, resetn, clk, e);

   initial begin
      $dumpfile("out.vcd");
      $dumpvars(0, tTr);
   end
endmodule // tTr

Language/verilog/third/timer/out.vcd
$date
	Fri Dec 14 01:20:01 2018
$end
$version
	Icarus Verilog
$end
$timescale
	1ns
$end
$scope module tTr $end
$var wire 5 ! q [4:0] $end
$var wire 1 " led $end
$var reg 1 # clk $end
$var reg 1 $ e $end
$var reg 1 % resetn $end
$scope module test $end
$var wire 1 # clk $end
$var wire 1 $ e $end
$var wire 1 % res $end
$var reg 1 " led $end
$var reg 5 & q [4:0] $end
$upscope $end
$upscope $end
$enddefinitions $end
#0
$dumpvars
bx &
1%
1$
1#
x"
bx !
$end
#25
0#
#50
1#
#75
0#
#100
1#
#125
0#
#150
1#
#175
0#
#200
1#
#225
0#
#250
1#
#275
0#
#300
1#
#325
0#
#350
1#
#375
0#
#400
1#
#425
0#
#450
1#
#475
0#
#500
1#
#525
0#
#550
1#
#575
0#
#600
1#
#625
0#
#650
1#
#675
0#
#700
1#
#725
0#
#750
0"
b0 !
b0 &
1#
0%
#775
0#
#800
1#
#825
0#
#850
1#
#875
0#
#900
1#
#925
0#
#950
1#
#975
0#
#1000
1#
#1025
0#
#1050
1#
#1075
0#
#1100
1#
#1125
0#
#1150
1#
#1175
0#
#1200
1#
#1225
0#
#1250
1#
#1275
0#
#1300
1#
#1325
0#
#1350
1#
#1375
0#
#1400
1#
#1425
0#
#1450
1#
#1475
0#
#1500
b1 !
b1 &
1#
1%
#1525
0#
#1550
b10 !
b10 &
1#
#1575
0#
#1600
b11 !
b11 &
1#
#1625
0#
#1650
b100 !
b100 &
1#
#1675
0#
#1700
b101 !
b101 &
1#
#1725
0#
#1750
b110 !
b110 &
1#
#1775
0#
#1800
b111 !
b111 &
1#
#1825
0#
#1850
b1000 !
b1000 &
1#
#1875
0#
#1900
b1001 !
b1001 &
1#
#1925
0#
#1950
b1010 !
b1010 &
1#
#1975
0#
#2000
b1011 !
b1011 &
1#
#2025
0#
#2050
b1100 !
b1100 &
1#
#2075
0#
#2100
b1101 !
b1101 &
1#
#2125
0#
#2150
b1110 !
b1110 &
1#
#2175
0#
#2200
b1111 !
b1111 &
1#
#2225
0#
#2250
b0 !
b0 &
1#
0%
#2275
0#
#2300
1#
#2325
0#
#2350
1#
#2375
0#
#2400
1#
#2425
0#
#2450
1#
#2475
0#
#2500
1#
#2525
0#
#2550
1#
#2575
0#
#2600
1#
#2625
0#
#2650
1#
#2675
0#
#2700
1#
#2725
0#
#2750
1#
#2775
0#
#2800
1#
#2825
0#
#2850
1#
#2875
0#
#2900
1#
#2925
0#
#2950
1#
#2975
0#
#3000
b1 !
b1 &
1#
1%
#3025
0#
#3050
b10 !
b10 &
1#
#3075
0#
#3100
b11 !
b11 &
1#
#3125
0#
#3150
b100 !
b100 &
1#
#3175
0#
#3200
b101 !
b101 &
1#
#3225
0#
#3250
b110 !
b110 &
1#
#3275
0#
#3300
b111 !
b111 &
1#
#3325
0#
#3350
b1000 !
b1000 &
1#
#3375
0#
#3400
b1001 !
b1001 &
1#
#3425
0#
#3450
b1010 !
b1010 &
1#
#3475
0#
#3500
b1011 !
b1011 &
1#
#3525
0#
#3550
b1100 !
b1100 &
1#
#3575
0#
#3600
b1101 !
b1101 &
1#
#3625
0#
#3650
b1110 !
b1110 &
1#
#3675
0#
#3700
b1111 !
b1111 &
1#
#3725
0#
#3750
b0 !
b0 &
1#
0%
#3775
0#
#3800
1#
#3825
0#
#3850
1#
#3875
0#
#3900
1#
#3925
0#
#3950
1#
#3975
0#
#4000
1#
#4025
0#
#4050
1#
#4075
0#
#4100
1#
#4125
0#
#4150
1#
#4175
0#
#4200
1#
#4225
0#
#4250
1#
#4275
0#
#4300
1#
#4325
0#
#4350
1#
#4375
0#
#4400
1#
#4425
0#
#4450
1#
#4475
0#
#4500
b1 !
b1 &
1#
1%
#4525
0#
#4550
b10 !
b10 &
1#
#4575
0#
#4600
b11 !
b11 &
1#
#4625
0#
#4650
b100 !
b100 &
1#
#4675
0#
#4700
b101 !
b101 &
1#
#4725
0#
#4750
b110 !
b110 &
1#
#4775
0#
#4800
b111 !
b111 &
1#
#4825
0#
#4850
b1000 !
b1000 &
1#
#4875
0#
#4900
b1001 !
b1001 &
1#
#4925
0#
#4950
b1010 !
b1010 &
1#
#4975
0#
#5000
b1011 !
b1011 &
1#
#5025
0#
#5050
b1100 !
b1100 &
1#
#5075
0#
#5100
b1101 !
b1101 &
1#
#5125
0#
#5150
b1110 !
b1110 &
1#
#5175
0#
#5200
b1111 !
b1111 &
1#
#5225
0#
#5250
b0 !
b0 &
1#
0%
#5275
0#
#5300
1#
#5325
0#
#5350
1#
#5375
0#
#5400
1#
#5425
0#
#5450
1#
#5475
0#
#5500
1#
#5525
0#
#5550
1#
#5575
0#
#5600
1#
#5625
0#
#5650
1#
#5675
0#
#5700
1#
#5725
0#
#5750
1#
#5775
0#
#5800
1#
#5825
0#
#5850
1#
#5875
0#
#5900
1#
#5925
0#
#5950
1#
#5975
0#
#6000
b1 !
b1 &
1#
1%
#6025
0#
#6050
b10 !
b10 &
1#
#6075
0#
#6100
b11 !
b11 &
1#
#6125
0#
#6150
b100 !
b100 &
1#
#6175
0#
#6200
b101 !
b101 &
1#
#6225
0#
#6250
b110 !
b110 &
1#
#6275
0#
#6300
b111 !
b111 &
1#
#6325
0#
#6350
b1000 !
b1000 &
1#
#6375
0#
#6400
b1001 !
b1001 &
1#
#6425
0#
#6450
b1010 !
b1010 &
1#
#6475
0#
#6500
b1011 !
b1011 &
1#
#6525
0#
#6550
b1100 !
b1100 &
1#
#6575
0#
#6600
b1101 !
b1101 &
1#
#6625
0#
#6650
b1110 !
b1110 &
1#
#6675
0#
#6700
b1111 !
b1111 &
1#
#6725
0#
#6750
b0 !
b0 &
1#
0%
#6775
0#
#6800
1#
#6825
0#
#6850
1#
#6875
0#
#6900
1#
#6925
0#
#6950
1#
#6975
0#
#7000
1#
#7025
0#
#7050
1#
#7075
0#
#7100
1#
#7125
0#
#7150
1#
#7175
0#
#7200
1#
#7225
0#
#7250
1#
#7275
0#
#7300
1#
#7325
0#
#7350
1#
#7375
0#
#7400
1#
#7425
0#
#7450
1#
#7475
0#
#7500
b1 !
b1 &
1#
1%
#7525
0#
#7550
b10 !
b10 &
1#
#7575
0#
#7600
b11 !
b11 &
1#
#7625
0#
#7650
b100 !
b100 &
1#
#7675
0#
#7700
b101 !
b101 &
1#
#7725
0#
#7750
b110 !
b110 &
1#
#7775
0#
#7800
b111 !
b111 &
1#
#7825
0#
#7850
b1000 !
b1000 &
1#
#7875
0#
#7900
b1001 !
b1001 &
1#
#7925
0#
#7950
b1010 !
b1010 &
1#
#7975
0#
#8000
b1011 !
b1011 &
1#
#8025
0#
#8050
b1100 !
b1100 &
1#
#8075
0#
#8100
b1101 !
b1101 &
1#
#8125
0#
#8150
b1110 !
b1110 &
1#
#8175
0#
#8200
b1111 !
b1111 &
1#
#8225
0#
#8250
b0 !
b0 &
1#
0%
#8275
0#
#8300
1#
#8325
0#
#8350
1#
#8375
0#
#8400
1#
#8425
0#
#8450
1#
#8475
0#
#8500
1#
#8525
0#
#8550
1#
#8575
0#
#8600
1#
#8625
0#
#8650
1#
#8675
0#
#8700
1#
#8725
0#
#8750
1#
#8775
0#
#8800
1#
#8825
0#
#8850
1#
#8875
0#
#8900
1#
#8925
0#
#8950
1#
#8975
0#
#9000
b1 !
b1 &
1#
1%
#9025
0#
#9050
b10 !
b10 &
1#
#9075
0#
#9100
b11 !
b11 &
1#
#9125
0#
#9150
b100 !
b100 &
1#
#9175
0#
#9200
b101 !
b101 &
1#
#9225
0#
#9250
b110 !
b110 &
1#
#9275
0#
#9300
b111 !
b111 &
1#
#9325
0#
#9350
b1000 !
b1000 &
1#
#9375
0#
#9400
b1001 !
b1001 &
1#
#9425
0#
#9450
b1010 !
b1010 &
1#
#9475
0#
#9500
b1011 !
b1011 &
1#
#9525
0#
#9550
b1100 !
b1100 &
1#
#9575
0#
#9600
b1101 !
b1101 &
1#
#9625
0#
#9650
b1110 !
b1110 &
1#
#9675
0#
#9700
b1111 !
b1111 &
1#
#9725
0#
#9750
b0 !
b0 &
1#
0%
