Language/verilog/dev/booth/booth.v
module booth (/*AUTOARG*/
   // Outputs
   c, finish,
   // Inputs
   a, b, CLK, Beg
   ) ;
   output [63:0] c;
   output reg        finish;
   input [31:0]      a, b;
   input             CLK, Beg;

   reg [64:0]        A, P;
   reg [64:0]        A_1, A2, A_2;
   reg [7:0]         index_i;


   reg [1:0]         current_state, next_state;
   parameter Init=0, Ready=1, Acc=2, Done=3;

   always @(posedge CLK or negedge Beg) begin
     if (!Beg) current_state <= Init;
     else current_state <= next_state;
   end
   always @ (current_state or index_i) begin
      case (current_state)
        Init: begin
           next_state = Ready;
           finish = 0;
        end
        Ready: begin
           next_state = Acc;
           A = {a[31:0], 33'h0};
           A2 = {a[30:0], 34'h0};
           A_2 = {(~a[30:0]) + 1'b1, 34'b0};
           A_1 = {(~a[31:0]) + 1'b1, 33'b0};
           P = {32'h0, b[31:0], 1'b0};
        end
        Acc: begin
           if (index_i == 8'h0f) next_state = Done;
           case (P[2:0])
             3'b001: begin
                P = P + A;
             end
             3'b010: begin
                P = P + A;
             end
             3'b011: begin
                P = P + A2;
             end
             3'b100: begin
                P = P + A_2;
             end
             3'b101: begin
                P = P + A_1;
             end
             3'b110: begin
                P = P + A_1;
             end
           endcase // case (cb[2:0])
           P = {P[64], P[64], P[64:2]};
        end
        default: begin
           finish = 1;
        end
      endcase // case (current_state)
   end

   always @ (posedge CLK) begin
      if (current_state == Acc) index_i <= index_i + 1;
      else index_i <= 0;
   end
   assign c = P[64:1];
endmodule // booth

Language/verilog/dev/booth/tb_booth.v
`timescale 1ns/1ns

module tb_booth;
   // Inputs
   reg [31:0] a;
   reg [31:0] b;
   reg        start;
   reg        clk;

   // Outputs
   wire       done;
   wire [63:0] c;

   // Instantiate the Unit Under Test (UUT)
   booth uut (
              .finish(done),
              .c(c),
              .a(a),
              .b(b),
              .Beg(start),
              .CLK(clk)
              );

   initial begin
      // Initialize Inputs
      a = 0;
      b = 0;
      start = 0;
      clk = 0;

      // Wait 100 ns for global reset to finish
      #100;

      // Add stimulus here
      start=1;

      a=32'h1101_1101;
      b=32'h1001_1011;

      #500;
      $stop;
   end
   always #10 clk=~clk;

   initial begin
      $dumpfile("out.vcd");
      $dumpvars(0, tb_booth);
   end
endmodule

Language/verilog/dev/booth/out.vcd
$date
	Thu Apr 11 18:03:12 2019
$end
$version
	Icarus Verilog
$end
$timescale
	1ns
$end
$scope module tb_booth $end
$var wire 1 ! done $end
$var wire 64 " c [63:0] $end
$var reg 32 # a [31:0] $end
$var reg 32 $ b [31:0] $end
$var reg 1 % clk $end
$var reg 1 & start $end
$scope module uut $end
$var wire 1 & Beg $end
$var wire 1 % CLK $end
$var wire 32 ' a [31:0] $end
$var wire 32 ( b [31:0] $end
$var wire 64 ) c [63:0] $end
$var reg 65 * A [64:0] $end
$var reg 65 + A2 [64:0] $end
$var reg 65 , A_1 [64:0] $end
$var reg 65 - A_2 [64:0] $end
$var reg 65 . P [64:0] $end
$var reg 2 / current_state [1:0] $end
$var reg 1 ! finish $end
$var reg 8 0 index_i [7:0] $end
$var reg 2 1 next_state [1:0] $end
$upscope $end
$upscope $end
$enddefinitions $end
#0
$dumpvars
b1 1
bx 0
b0 /
bx .
bx -
bx ,
bx +
bx *
bx )
b0 (
b0 '
0&
0%
b0 $
b0 #
bx "
0!
$end
#10
b0 0
1%
#20
0%
#30
1%
#40
0%
#50
1%
#60
0%
#70
1%
#80
0%
#90
1%
#100
0%
b10000000000010001000000010001 $
b10000000000010001000000010001 (
b10001000000010001000100000001 #
b10001000000010001000100000001 '
1&
#110
b10000000000010001000000010001 "
b10000000000010001000000010001 )
b100000000000100010000000100010 .
b11101110111111101110111011111111000000000000000000000000000000000 ,
b11011101111111011101110111111110000000000000000000000000000000000 -
b100010000000100010001000000010000000000000000000000000000000000 +
b10001000000010001000100000001000000000000000000000000000000000 *
b10 1
b1 /
1%
#120
0%
#130
b10001000000010001000100000001000100000000000100010000000100 "
b10001000000010001000100000001000100000000000100010000000100 )
b100010000000100010001000000010001000000000001000100000001000 .
b10 /
1%
#140
0%
#150
b100010000000100010001000000010001000000000001000100000001 "
b100010000000100010001000000010001000000000001000100000001 )
b1000100000001000100010000000100010000000000010001000000010 .
b1 0
1%
#160
0%
#170
b10010000100010010001000010001000100010000000000010001000000 "
b10010000100010010001000010001000100010000000000010001000000 )
b100100001000100100010000100010001000100000000000100010000000 .
b10 0
1%
#180
0%
#190
b100100001000100100010000100010001000100000000000100010000 "
b100100001000100100010000100010001000100000000000100010000 )
b1001000010001001000100001000100010001000000000001000100000 .
b11 0
1%
#200
0%
#210
b1001000010001001000100001000100010001000000000001000100 "
b1001000010001001000100001000100010001000000000001000100 )
b10010000100010010001000010001000100010000000000010001000 .
b100 0
1%
#220
0%
#230
b10010000100010010001000010001000100010000000000010001 "
b10010000100010010001000010001000100010000000000010001 )
b100100001000100100010000100010001000100000000000100010 .
b101 0
1%
#240
0%
#250
b10001000100110010001000100011000100010001000100000000000100 "
b10001000100110010001000100011000100010001000100000000000100 )
b100010001001100100010001000110001000100010001000000000001000 .
b110 0
1%
#260
0%
#270
b100010001001100100010001000110001000100010001000000000001 "
b100010001001100100010001000110001000100010001000000000001 )
b1000100010011001000100010001100010001000100010000000000010 .
b111 0
1%
#280
0%
#290
b10010000100100100001100100011001100010001000100010000000000 "
b10010000100100100001100100011001100010001000100010000000000 )
b100100001001001000011001000110011000100010001000100000000000 .
b1000 0
1%
#300
0%
#310
b100100001001001000011001000110011000100010001000100000000 "
b100100001001001000011001000110011000100010001000100000000 )
b1001000010010010000110010001100110001000100010001000000000 .
b1001 0
1%
#320
0%
#330
b1001000010010010000110010001100110001000100010001000000 "
b1001000010010010000110010001100110001000100010001000000 )
b10010000100100100001100100011001100010001000100010000000 .
b1010 0
1%
#340
0%
#350
b10010000100100100001100100011001100010001000100010000 "
b10010000100100100001100100011001100010001000100010000 )
b100100001001001000011001000110011000100010001000100000 .
b1011 0
1%
#360
0%
#370
b100100001001001000011001000110011000100010001000100 "
b100100001001001000011001000110011000100010001000100 )
b1001000010010010000110010001100110001000100010001000 .
b1100 0
1%
#380
0%
#390
b1001000010010010000110010001100110001000100010001 "
b1001000010010010000110010001100110001000100010001 )
b10010000100100100001100100011001100010001000100010 .
b1101 0
1%
#400
0%
#410
b10001000000100011001000100101001100100011001100010001000100 "
b10001000000100011001000100101001100100011001100010001000100 )
b100010000001000110010001001010011001000110011000100010001000 .
b1110 0
1%
#420
0%
#430
b100010000001000110010001001010011001000110011000100010001 "
b100010000001000110010001001010011001000110011000100010001 )
b1000100000010001100100010010100110010001100110001000100010 .
b11 1
b1111 0
1%
#440
0%
#450
1!
b10000 0
b11 /
1%
#460
0%
#470
b0 0
1%
