Language/verilog/third/Dtriggrt/d.v
module d (/*AUTOARG*/
   // Outputs
   q, nq,
   // Inputs
   d, clock
   ) ;
   input d, clock;
   output q, nq;

   reg    q, nq;


   always @ (posedge clock) begin
      q = d ? 1 : 0;
      nq = ~q;
   end

endmodule // d

Language/verilog/third/Dtriggrt/td.v
`timescale 1ns/1ns

module td (/*AUTOARG*/) ;
   wire q, nq;
   reg  clock, d;

   always #10 clock = ~clock;

   initial begin
      #0 clock = 0; d = 0;
      #5 d = 1;
      #25 d = 0;
      #45 d = 1;
      #55 d = 0;
      #62 d = 1;
      #63 d = 0;
      #75 d = 1;
      #85 d = 0;
      #100 $stop;
   end

   d test(q, nq, d, clock);

   initial begin
      $dumpfile("out.vcd");
      $dumpvars(0, td);
   end
endmodule // td

Language/verilog/third/Dtriggrt/out.vcd
$date
	Fri Dec  7 22:16:12 2018
$end
$version
	Icarus Verilog
$end
$timescale
	1ns
$end
$scope module td $end
$var wire 1 ! q $end
$var wire 1 " nq $end
$var reg 1 # clock $end
$var reg 1 $ d $end
$scope module test $end
$var wire 1 # clock $end
$var wire 1 $ d $end
$var reg 1 " nq $end
$var reg 1 ! q $end
$upscope $end
$upscope $end
$enddefinitions $end
#0
$dumpvars
0$
0#
x"
x!
$end
#5
1$
#10
0"
1!
1#
#20
0#
#30
1"
0!
1#
0$
#40
0#
#50
1#
#60
0#
#70
1#
#75
1$
#80
0#
#90
0"
1!
1#
#100
0#
#110
1#
#120
0#
#130
1"
0!
1#
0$
#140
0#
#150
1#
#160
0#
#170
1#
#180
0#
#190
1#
#192
1$
#200
0#
#210
0"
1!
1#
#220
0#
#230
1#
#240
0#
#250
1#
#255
0$
#260
0#
#270
1"
0!
1#
#280
0#
#290
1#
#300
0#
#310
1#
#320
0#
#330
0"
1!
1#
1$
#340
0#
#350
1#
#360
0#
#370
1#
#380
0#
#390
1#
#400
0#
#410
1#
#415
0$
#420
0#
#430
1"
0!
1#
