Language/verilog/second/switcher21/swi21.v
module swi21 (/*AUTOARG*/
   // Outputs
   f,
   // Inputs
   x0, x1, m
   ) ;
   input x0, x1, m;
   output f;

   assign f = (~m & x0) | (m & x1);
endmodule // swi21

Language/verilog/second/switcher21/tswi21.v
`timescale 1ns/1ns

module tswi21 (/*AUTOARG*/ ) ;
   reg x1, x0, m;
   wire f;

   always #40 m = ~m;
   always #10 x0 = ~x0;
   always #20 x1 = ~x1;

   initial begin
      #0 m = 0; x0 = 0; x1 = 0;
      #100 $stop;
   end

   swi21 test(f, x1, x0, m);

   initial begin
      $dumpfile("out.vcd");
      $dumpvars(0, tswi21);
   end

endmodule // tswi21

Language/verilog/second/switcher21/out.vcd
$date
	Sun Dec  2 20:36:24 2018
$end
$version
	Icarus Verilog
$end
$timescale
	1ns
$end
$scope module tswi21 $end
$var wire 1 ! f $end
$var reg 1 " m $end
$var reg 1 # x0 $end
$var reg 1 $ x1 $end
$scope module test $end
$var wire 1 ! f $end
$var wire 1 " m $end
$var wire 1 $ x0 $end
$var wire 1 # x1 $end
$upscope $end
$upscope $end
$enddefinitions $end
#0
$dumpvars
0$
0#
0"
0!
$end
#10
1#
#20
1!
0#
1$
#30
1#
#40
0!
0#
0$
1"
#50
1!
1#
#60
0!
0#
1$
#70
1!
1#
#80
0!
0#
0$
0"
#90
1#
